dp_periodic_table/__init__.py
dp_periodic_table/frontend/build/asset-manifest.json
dp_periodic_table/frontend/build/bootstrap.min.css
dp_periodic_table/frontend/build/index.html
dp_periodic_table/frontend/build/static/css/main.b495fb7d.css
dp_periodic_table/frontend/build/static/css/main.b495fb7d.css.map
dp_periodic_table/frontend/build/static/css/main.bc4a2fd9.css
dp_periodic_table/frontend/build/static/css/main.bc4a2fd9.css.map
dp_periodic_table/frontend/build/static/css/main.bc729b6b.css
dp_periodic_table/frontend/build/static/css/main.bc729b6b.css.map
dp_periodic_table/frontend/build/static/css/main.c3d1dc71.css
dp_periodic_table/frontend/build/static/css/main.c3d1dc71.css.map
dp_periodic_table/frontend/build/static/js/main.14d6debd.js
dp_periodic_table/frontend/build/static/js/main.14d6debd.js.LICENSE.txt
dp_periodic_table/frontend/build/static/js/main.14d6debd.js.map
dp_periodic_table/frontend/build/static/js/main.74a04d56.js
dp_periodic_table/frontend/build/static/js/main.74a04d56.js.LICENSE.txt
dp_periodic_table/frontend/build/static/js/main.74a04d56.js.map
dp_periodic_table/frontend/build/static/js/main.9a473e6c.js
dp_periodic_table/frontend/build/static/js/main.9a473e6c.js.LICENSE.txt
dp_periodic_table/frontend/build/static/js/main.9a473e6c.js.map
dp_periodic_table/frontend/build/static/js/main.b67ef791.js
dp_periodic_table/frontend/build/static/js/main.b67ef791.js.LICENSE.txt
dp_periodic_table/frontend/build/static/js/main.b67ef791.js.map
dp_periodic_table-0.0.6.dist-info/LICENSE
dp_periodic_table-0.0.6.dist-info/METADATA
dp_periodic_table-0.0.6.dist-info/WHEEL
dp_periodic_table-0.0.6.dist-info/top_level.txt
dp_periodic_table-0.0.6.dist-info/RECORD
